gan_mealnizer/data/10780.json
gan_mealnizer/data/13116.json
gan_mealnizer/data/14842.json
gan_mealnizer/data/17172.json
gan_mealnizer/data/2.json
gan_mealnizer/data/20566.json
gan_mealnizer/data/21632.json
gan_mealnizer/data/2627.json
gan_mealnizer/data/27366.json
gan_mealnizer/data/29127.json
gan_mealnizer/data/30024.json
gan_mealnizer/data/30332.json
gan_mealnizer/data/31870.json
gan_mealnizer/data/33550.json
gan_mealnizer/data/34407.json
gan_mealnizer/data/34429.json
gan_mealnizer/data/36495.json
gan_mealnizer/data/37327.json
gan_mealnizer/data/38639.json
gan_mealnizer/data/7.json
gan_mealnizer/data/README
gan_mealnizer/data/relationship.png
gan_mealnizer/main.py
gan_mealnizer/Pipfile.lock
gan_mealnizer/README.md
gan_mealnizer/requirements.txt
gan_mealnizer/test_main.py
gan_mealnizer-2.0.dist-info/entry_points.txt
gan_mealnizer-2.0.dist-info/WHEEL
gan_mealnizer-2.0.dist-info/METADATA
gan_mealnizer-2.0.dist-info/RECORD
