Metadata-Version: 2.1
Name: gan-mealnizer
Version: 2.0
Summary: 
Author: Gan Mahmud
Author-email: ganmahmud@users.noreply.github.com
Requires-Python: >=3.9,<4.0
Classifier: Programming Language :: Python :: 3
Classifier: Programming Language :: Python :: 3.10
Classifier: Programming Language :: Python :: 3.9
Requires-Dist: typer[all] (>=0.4.0,<0.5.0)
